grand_challenge_dicom_de_identifier/__init__.py
grand_challenge_dicom_de_identifier/deidentifier.py
grand_challenge_dicom_de_identifier/exceptions.py
grand_challenge_dicom_de_identifier/models.py
grand_challenge_dicom_de_identifier/typing.py
grand_challenge_dicom_de_identifier-0.1.1.dist-info/licenses/LICENCE.md
grand_challenge_dicom_de_identifier-0.1.1.dist-info/METADATA
grand_challenge_dicom_de_identifier-0.1.1.dist-info/WHEEL
grand_challenge_dicom_de_identifier-0.1.1.dist-info/top_level.txt
grand_challenge_dicom_de_identifier-0.1.1.dist-info/RECORD
